dmsuploader/__init__.py
dmsuploader/attributes.py
dmsuploader/color_format.py
dmsuploader/custom_logger.py
dmsuploader/main.py
dmsuploader-0.0.4.dist-info/METADATA
dmsuploader-0.0.4.dist-info/WHEEL
dmsuploader-0.0.4.dist-info/top_level.txt
dmsuploader-0.0.4.dist-info/RECORD
