Metadata-Version: 2.1
Name: dmsuploader
Version: 0.0.4
Summary: Upload Files to DMS
Author: MTLM
Keywords: python,dms,uploader
Classifier: Development Status :: 1 - Planning
Classifier: Intended Audience :: Developers
Classifier: Programming Language :: Python :: 3
Classifier: Operating System :: Unix
Classifier: Operating System :: MacOS :: MacOS X
Requires-Dist: tqdm >=4.66.1
Requires-Dist: requests >=2.31.0
